{
  "as_of": "2026-01-14",
  "most_traded": [
    {
      "symbol": "TSLA",
      "close": 436.4800109863281,
      "volume": 39515850,
      "turnover_eur": 17247878642.134094,
      "change_pct": -2.397137953507099,
      "drawdown_pct": -10.900627370831062,
      "trend10y_cagr": 41.31260756842509
    },
    {
      "symbol": "NVDA",
      "close": 181.94000244140625,
      "volume": 68785013,
      "turnover_eur": 12514745433.15216,
      "change_pct": -2.0827701243401218,
      "drawdown_pct": -12.123257176712688,
      "trend10y_cagr": 73.96266329045682
    },
    {
      "symbol": "MSFT",
      "close": 459.3599853515625,
      "volume": 14101592,
      "turnover_eur": 6477707094.553711,
      "change_pct": -2.4029633827327714,
      "drawdown_pct": -15.258180835521928,
      "trend10y_cagr": 24.078828811373864
    },
    {
      "symbol": "AMD",
      "close": 221.88499450683594,
      "volume": 28777639,
      "turnover_eur": 6385326271.434708,
      "change_pct": 0.41408031908318826,
      "drawdown_pct": -16.05757735466974,
      "trend10y_cagr": 58.55267194082781
    },
    {
      "symbol": "AMZN",
      "close": 237.11000061035156,
      "volume": 23869307,
      "turnover_eur": 5659651397.338669,
      "change_pct": -2.262986543710769,
      "drawdown_pct": -6.649606058916713,
      "trend10y_cagr": 23.10976943686207
    },
    {
      "symbol": "META",
      "close": 616.7750244140625,
      "volume": 8962827,
      "turnover_eur": 5528047841.744019,
      "change_pct": -2.268297997471706,
      "drawdown_pct": -20.951614942125918,
      "trend10y_cagr": 20.150728830244912
    }
  ],
  "most_bought": [
    {
      "symbol": "LYB",
      "close": 52.31999969482422,
      "volume": 5752168,
      "turnover_eur": 300953428.00457764,
      "change_pct": 7.4994897538497325,
      "drawdown_pct": -5.678747893560942,
      "trend10y_cagr": -3.711484165929324
    },
    {
      "symbol": "DOW",
      "close": 28.46500015258789,
      "volume": 11650127,
      "turnover_eur": 331620866.8326683,
      "change_pct": 7.212809681946195,
      "drawdown_pct": 0,
      "trend10y_cagr": -5.439842818870233
    },
    {
      "symbol": "DVN",
      "close": 38.51539993286133,
      "volume": 7609995,
      "turnover_eur": 293102000.91207504,
      "change_pct": 4.547773543252133,
      "drawdown_pct": 0,
      "trend10y_cagr": 4.0238621203736225
    },
    {
      "symbol": "ACN",
      "close": 289.3800048828125,
      "volume": 3745867,
      "turnover_eur": 1083979010.7503662,
      "change_pct": 4.544804062366113,
      "drawdown_pct": 0,
      "trend10y_cagr": 11.003828942080496
    },
    {
      "symbol": "COP",
      "close": 100.58000183105469,
      "volume": 4698483,
      "turnover_eur": 472573428.7431793,
      "change_pct": 4.271203385533968,
      "drawdown_pct": 0,
      "trend10y_cagr": 9.32230214438281
    },
    {
      "symbol": "NOC",
      "close": 650.932373046875,
      "volume": 585605,
      "turnover_eur": 381189252.31811523,
      "change_pct": 4.065926945943246,
      "drawdown_pct": 0,
      "trend10y_cagr": 13.372439190816277
    }
  ],
  "most_sold": [
    {
      "symbol": "APP",
      "close": 604.7650146484375,
      "volume": 6217764,
      "turnover_eur": 3760286136.5405273,
      "change_pct": -9.551618947398016,
      "drawdown_pct": -17.562018160455573,
      "trend10y_cagr": 24.94932329745869
    },
    {
      "symbol": "INTU",
      "close": 563.6300048828125,
      "volume": 3082340,
      "turnover_eur": 1737299309.2504883,
      "change_pct": -6.881116573835312,
      "drawdown_pct": -19.721120750396224,
      "trend10y_cagr": 19.574626062480462
    },
    {
      "symbol": "ABNB",
      "close": 131.31500244140625,
      "volume": 3720423,
      "turnover_eur": 488547355.32806396,
      "change_pct": -6.250449364614775,
      "drawdown_pct": -6.250449364614774,
      "trend10y_cagr": -0.9666253568816452
    },
    {
      "symbol": "RCL",
      "close": 276.2601013183594,
      "volume": 1566491,
      "turnover_eur": 432758962.3742981,
      "change_pct": -5.299568023327765,
      "drawdown_pct": -21.30686969760771,
      "trend10y_cagr": 12.132867549763748
    },
    {
      "symbol": "ORCL",
      "close": 192.1300048828125,
      "volume": 14596655,
      "turnover_eur": 2804455396.4227295,
      "change_pct": -5.022486895310402,
      "drawdown_pct": -41.48265076588593,
      "trend10y_cagr": 18.635338936693735
    },
    {
      "symbol": "AVGO",
      "close": 337.2875061035156,
      "volume": 16255567,
      "turnover_eur": 5482799653.728607,
      "change_pct": -4.884938372751479,
      "drawdown_pct": -18.32639051104843,
      "trend10y_cagr": 39.009045503987934
    }
  ],
  "turnarounds": [
    {
      "symbol": "SMCI",
      "close": 28.19499969482422,
      "volume": 17755321,
      "turnover_eur": 500611270.17650604,
      "change_pct": -1.416086298054431,
      "drawdown_pct": -51.95126184698176,
      "trend10y_cagr": 27.699537475371947
    },
    {
      "symbol": "FISV",
      "close": 66.74500274658203,
      "volume": 8009201,
      "turnover_eur": 534574142.74292755,
      "change_pct": -0.007486521974485019,
      "drawdown_pct": -51.07030206383478,
      "trend10y_cagr": 4.133685292622413
    },
    {
      "symbol": "ORCL",
      "close": 192.1300048828125,
      "volume": 14596655,
      "turnover_eur": 2804455396.4227295,
      "change_pct": -5.022486895310402,
      "drawdown_pct": -41.48265076588593,
      "trend10y_cagr": 18.635338936693735
    },
    {
      "symbol": "DDOG",
      "close": 121.46499633789062,
      "volume": 2299498,
      "turnover_eur": 279308516.1489868,
      "change_pct": -3.2151423602465137,
      "drawdown_pct": -39.18235750275998,
      "trend10y_cagr": 12.456385578352847
    },
    {
      "symbol": "LW",
      "close": 43.375,
      "volume": 1823754,
      "turnover_eur": 79105329.75,
      "change_pct": 3.594461682608615,
      "drawdown_pct": -34.843022083756466,
      "trend10y_cagr": 3.642220220835757
    },
    {
      "symbol": "TTD",
      "close": 36.4900016784668,
      "volume": 5126542,
      "turnover_eur": 187067526.18473053,
      "change_pct": -1.750128491824387,
      "drawdown_pct": -32.58821178933823,
      "trend10y_cagr": 28.33961700206944
    }
  ]
}