{
  "as_of": "2026-03-05",
  "most_traded": [
    {
      "symbol": "NVDA",
      "close": 180.47999572753906,
      "volume": 142016749,
      "turnover_eur": 25631182252.758987,
      "change_pct": -1.3986001160915125,
      "drawdown_pct": -12.828438185798907,
      "trend10y_cagr": 71.74136296952456
    },
    {
      "symbol": "TSLA",
      "close": 400.5849914550781,
      "volume": 39194155,
      "turnover_eur": 15700590245.764008,
      "change_pct": -1.3191631655224891,
      "drawdown_pct": -18.22793593077865,
      "trend10y_cagr": 40.1672955911818
    },
    {
      "symbol": "AVGO",
      "close": 326.489990234375,
      "volume": 41492586,
      "turnover_eur": 13546913997.938965,
      "change_pct": 2.821777938942354,
      "drawdown_pct": -20.940991047945566,
      "trend10y_cagr": 36.6780490898307
    },
    {
      "symbol": "MSFT",
      "close": 409.0249938964844,
      "volume": 22960873,
      "turnover_eur": 9391570938.682953,
      "change_pct": 0.9439737350004828,
      "drawdown_pct": -24.543880242420148,
      "trend10y_cagr": 23.14155313891586
    },
    {
      "symbol": "AMZN",
      "close": 217.3699951171875,
      "volume": 38868061,
      "turnover_eur": 8448750229.784546,
      "change_pct": 0.25366099732038727,
      "drawdown_pct": -14.421261764886806,
      "trend10y_cagr": 22.683893748891126
    },
    {
      "symbol": "MU",
      "close": 385.54998779296875,
      "volume": 21339822,
      "turnover_eur": 8227568111.604126,
      "change_pct": -3.7976898565086694,
      "drawdown_pct": -11.934673699604692,
      "trend10y_cagr": 41.98328293969067
    }
  ],
  "most_bought": [
    {
      "symbol": "TTD",
      "close": 29.88800048828125,
      "volume": 67618167,
      "turnover_eur": 2020971808.312683,
      "change_pct": 18.744538727399114,
      "drawdown_pct": -44.24920696137771,
      "trend10y_cagr": 25.803590634949238
    },
    {
      "symbol": "EXPE",
      "close": 249.3000030517578,
      "volume": 4789062,
      "turnover_eur": 1193913171.2150574,
      "change_pct": 12.434044944508395,
      "drawdown_pct": -17.261290673477202,
      "trend10y_cagr": 8.991414312298861
    },
    {
      "symbol": "BKNG",
      "close": 4595.2548828125,
      "volume": 587495,
      "turnover_eur": 2699689267.3779297,
      "change_pct": 8.032640702937277,
      "drawdown_pct": -16.32988055218775,
      "trend10y_cagr": 13.533459525843995
    },
    {
      "symbol": "LYB",
      "close": 66.16000366210938,
      "volume": 12119717,
      "turnover_eur": 801840521.1037292,
      "change_pct": 6.847554293518292,
      "drawdown_pct": 0,
      "trend10y_cagr": -2.3869872051098584
    },
    {
      "symbol": "INTU",
      "close": 469.29998779296875,
      "volume": 5111127,
      "turnover_eur": 2398651838.708313,
      "change_pct": 6.625158398248071,
      "drawdown_pct": -31.327649258323596,
      "trend10y_cagr": 16.79255416950156
    },
    {
      "symbol": "NOW",
      "close": 121.00499725341797,
      "volume": 20096469,
      "turnover_eur": 2431773176.1483994,
      "change_pct": 6.275247325456997,
      "drawdown_pct": -36.0634688820928,
      "trend10y_cagr": 26.377602092633424
    }
  ],
  "most_sold": [
    {
      "symbol": "CIEN",
      "close": 296.57000732421875,
      "volume": 5687993,
      "turnover_eur": 1686888125.670105,
      "change_pct": -13.674860176988634,
      "drawdown_pct": -16.15921801566298,
      "trend10y_cagr": 33.128224617051295
    },
    {
      "symbol": "GLW",
      "close": 132.7100067138672,
      "volume": 13937723,
      "turnover_eur": 1849675312.906021,
      "change_pct": -8.374751402040868,
      "drawdown_pct": -17.27855589816948,
      "trend10y_cagr": 21.096414712175225
    },
    {
      "symbol": "MRNA",
      "close": 53.3650016784668,
      "volume": 9829381,
      "turnover_eur": 524544933.56328964,
      "change_pct": -7.673006258017547,
      "drawdown_pct": -7.673006258017545,
      "trend10y_cagr": 11.115426461708644
    },
    {
      "symbol": "FIX",
      "close": 1327.6700439453125,
      "volume": 374141,
      "turnover_eur": 496735797.91174316,
      "change_pct": -7.1806065931350025,
      "drawdown_pct": -9.5949772110418,
      "trend10y_cagr": 45.883902956143665
    },
    {
      "symbol": "UAL",
      "close": 93.80999755859375,
      "volume": 8847939,
      "turnover_eur": 830025135.9885864,
      "change_pct": -6.638142491542405,
      "drawdown_pct": -20.18208241901339,
      "trend10y_cagr": 4.996573045761887
    },
    {
      "symbol": "FCX",
      "close": 61.7400016784668,
      "volume": 13218633,
      "turnover_eur": 816118423.6070366,
      "change_pct": -6.355223126519616,
      "drawdown_pct": -10.287704225156935,
      "trend10y_cagr": 20.13483983502713
    }
  ],
  "turnarounds": [
    {
      "symbol": "FISV",
      "close": 63.735198974609375,
      "volume": 3513282,
      "turnover_eur": 223919727.32391357,
      "change_pct": 1.813419374055695,
      "drawdown_pct": -49.632370386059776,
      "trend10y_cagr": 2.815054759512714
    },
    {
      "symbol": "HOOD",
      "close": 79.31999969482422,
      "volume": 31365210,
      "turnover_eur": 2487888447.6280975,
      "change_pct": -3.5153867191737795,
      "drawdown_pct": -46.07016677499356,
      "trend10y_cagr": 8.581389282782471
    },
    {
      "symbol": "ORCL",
      "close": 152.94000244140625,
      "volume": 17543457,
      "turnover_eur": 2683096356.4107056,
      "change_pct": 0.37409420652692044,
      "drawdown_pct": -46.02053799822644,
      "trend10y_cagr": 14.832348982518306
    },
    {
      "symbol": "TTD",
      "close": 29.88800048828125,
      "volume": 67618167,
      "turnover_eur": 2020971808.312683,
      "change_pct": 18.744538727399114,
      "drawdown_pct": -44.24920696137771,
      "trend10y_cagr": 25.803590634949238
    },
    {
      "symbol": "SMCI",
      "close": 31.790000915527344,
      "volume": 20391400,
      "turnover_eur": 648242624.6688843,
      "change_pct": -2.63399868349137,
      "drawdown_pct": -39.66596746234733,
      "trend10y_cagr": 25.4879330233603
    },
    {
      "symbol": "WDAY",
      "close": 147.25999450683594,
      "volume": 3790138,
      "turnover_eur": 558135701.0601501,
      "change_pct": 2.9502247055210384,
      "drawdown_pct": -39.33676848328077,
      "trend10y_cagr": 7.335833846607742
    }
  ]
}