{
  "as_of": "2026-05-06",
  "most_traded": [
    {
      "symbol": "SAP.DE",
      "name": "SAP",
      "close": 149.32000732421875,
      "volume": 5134894,
      "turnover_eur": 766742409.6890869,
      "change_pct": -0.3204243776772273,
      "drawdown_pct": -30.044502478757973,
      "trend10y_cagr": 8.284212821201509
    },
    {
      "symbol": "IFX.DE",
      "name": "Infineon",
      "close": 59.22999954223633,
      "volume": 11867373,
      "turnover_eur": 702904497.3575478,
      "change_pct": -2.0991743103531766,
      "drawdown_pct": -2.09917431035318,
      "trend10y_cagr": 17.32005433558188
    },
    {
      "symbol": "ENR.DE",
      "name": "Siemens Energy",
      "close": 185.83999633789062,
      "volume": 2681470,
      "turnover_eur": 498324374.9801636,
      "change_pct": 1.796668943449202,
      "drawdown_pct": -0.9487255226635516,
      "trend10y_cagr": 23.786034572696902
    },
    {
      "symbol": "RHM.DE",
      "name": "Rheinmetall",
      "close": 1441.5999755859375,
      "volume": 296812,
      "turnover_eur": 427884171.9536133,
      "change_pct": 0.4319319399765129,
      "drawdown_pct": -24.91666793823242,
      "trend10y_cagr": 36.1411275021897
    },
    {
      "symbol": "SIE.DE",
      "name": "Siemens",
      "close": 268.29998779296875,
      "volume": 1551545,
      "turnover_eur": 416279504.5602417,
      "change_pct": 2.9942371566098847,
      "drawdown_pct": 0,
      "trend10y_cagr": 12.375987740914262
    },
    {
      "symbol": "ALV.DE",
      "name": "Allianz",
      "close": 392.5,
      "volume": 900654,
      "turnover_eur": 353506695,
      "change_pct": 2.507183665850606,
      "drawdown_pct": -0.5825703809734795,
      "trend10y_cagr": 10.91065418470054
    }
  ],
  "most_bought": [
    {
      "symbol": "MTX.DE",
      "name": "MTU Aero Engines",
      "close": 314.8999938964844,
      "volume": 571571,
      "turnover_eur": 179987704.41140747,
      "change_pct": 10.143407002135163,
      "drawdown_pct": -21.66666818495414,
      "trend10y_cagr": 14.244753125015187
    },
    {
      "symbol": "BMW.DE",
      "name": "BMW",
      "close": 81.4000015258789,
      "volume": 2391139,
      "turnover_eur": 194638718.24858856,
      "change_pct": 5.413105722737413,
      "drawdown_pct": -15.49003137065733,
      "trend10y_cagr": 0.7299432740428102
    },
    {
      "symbol": "MBG.DE",
      "name": "Mercedes-Benz Group",
      "close": 50.18000030517578,
      "volume": 5890618,
      "turnover_eur": 295591213.03767395,
      "change_pct": 4.129491046226865,
      "drawdown_pct": -18.97303397723058,
      "trend10y_cagr": 0.1556081793664621
    },
    {
      "symbol": "DBK.DE",
      "name": "Deutsche Bank",
      "close": 27.25,
      "volume": 6484524,
      "turnover_eur": 176703279,
      "change_pct": 3.8688750372963527,
      "drawdown_pct": -19.402546899844964,
      "trend10y_cagr": 7.553792208436061
    },
    {
      "symbol": "SIE.DE",
      "name": "Siemens",
      "close": 268.29998779296875,
      "volume": 1551545,
      "turnover_eur": 416279504.5602417,
      "change_pct": 2.9942371566098847,
      "drawdown_pct": 0,
      "trend10y_cagr": 12.375987740914262
    },
    {
      "symbol": "ALV.DE",
      "name": "Allianz",
      "close": 392.5,
      "volume": 900654,
      "turnover_eur": 353506695,
      "change_pct": 2.507183665850606,
      "drawdown_pct": -0.5825703809734795,
      "trend10y_cagr": 10.91065418470054
    }
  ],
  "most_sold": [
    {
      "symbol": "IFX.DE",
      "name": "Infineon",
      "close": 59.22999954223633,
      "volume": 11867373,
      "turnover_eur": 702904497.3575478,
      "change_pct": -2.0991743103531766,
      "drawdown_pct": -2.09917431035318,
      "trend10y_cagr": 17.32005433558188
    },
    {
      "symbol": "BAS.DE",
      "name": "BASF",
      "close": 52.52000045776367,
      "volume": 5848265,
      "turnover_eur": 307150880.47712326,
      "change_pct": -1.7399444188981454,
      "drawdown_pct": -4.0555373632303215,
      "trend10y_cagr": -2.6071979387194633
    },
    {
      "symbol": "SAP.DE",
      "name": "SAP",
      "close": 149.32000732421875,
      "volume": 5134894,
      "turnover_eur": 766742409.6890869,
      "change_pct": -0.3204243776772273,
      "drawdown_pct": -30.044502478757973,
      "trend10y_cagr": 8.284212821201509
    },
    {
      "symbol": "RHM.DE",
      "name": "Rheinmetall",
      "close": 1441.5999755859375,
      "volume": 296812,
      "turnover_eur": 427884171.9536133,
      "change_pct": 0.4319319399765129,
      "drawdown_pct": -24.91666793823242,
      "trend10y_cagr": 36.1411275021897
    },
    {
      "symbol": "DTE.DE",
      "name": "Deutsche Telekom",
      "close": 27.81999969482422,
      "volume": 8590615,
      "turnover_eur": 238990906.67835236,
      "change_pct": 1.7556676648039207,
      "drawdown_pct": -18.39249172689632,
      "trend10y_cagr": 6.37536552536202
    },
    {
      "symbol": "ENR.DE",
      "name": "Siemens Energy",
      "close": 185.83999633789062,
      "volume": 2681470,
      "turnover_eur": 498324374.9801636,
      "change_pct": 1.796668943449202,
      "drawdown_pct": -0.9487255226635516,
      "trend10y_cagr": 23.786034572696902
    }
  ],
  "turnarounds": [
    {
      "symbol": "QIA.DE",
      "name": "Qiagen",
      "close": 29.2450008392334,
      "volume": 621943,
      "turnover_eur": 18188723.556955338,
      "change_pct": 0.8796173512539452,
      "drawdown_pct": -37.012705907793595,
      "trend10y_cagr": 2.8739519149516113
    },
    {
      "symbol": "SAP.DE",
      "name": "SAP",
      "close": 149.32000732421875,
      "volume": 5134894,
      "turnover_eur": 766742409.6890869,
      "change_pct": -0.3204243776772273,
      "drawdown_pct": -30.044502478757973,
      "trend10y_cagr": 8.284212821201509
    },
    {
      "symbol": "RHM.DE",
      "name": "Rheinmetall",
      "close": 1441.5999755859375,
      "volume": 296812,
      "turnover_eur": 427884171.9536133,
      "change_pct": 0.4319319399765129,
      "drawdown_pct": -24.91666793823242,
      "trend10y_cagr": 36.1411275021897
    },
    {
      "symbol": "SHL.DE",
      "name": "Siemens Healthineers",
      "close": 35.61000061035156,
      "volume": 1801838,
      "turnover_eur": 64163452.27975464,
      "change_pct": 1.1647722685386426,
      "drawdown_pct": -24.314556455290813,
      "trend10y_cagr": 0.9335915079818236
    },
    {
      "symbol": "MTX.DE",
      "name": "MTU Aero Engines",
      "close": 314.8999938964844,
      "volume": 571571,
      "turnover_eur": 179987704.41140747,
      "change_pct": 10.143407002135163,
      "drawdown_pct": -21.66666818495414,
      "trend10y_cagr": 14.244753125015187
    },
    {
      "symbol": "HEI.DE",
      "name": "Heidelberg Materials",
      "close": 189.14999389648438,
      "volume": 549275,
      "turnover_eur": 103895362.89749146,
      "change_pct": 2.464782038207147,
      "drawdown_pct": -20.857743139546294,
      "trend10y_cagr": 9.476314434932664
    }
  ]
}