{
  "as_of": "2026-02-18",
  "most_traded": [
    {
      "symbol": "NVDA",
      "close": 188.5800018310547,
      "volume": 104033315,
      "turnover_eur": 19618602733.19069,
      "change_pct": 1.9516681551210942,
      "drawdown_pct": -8.91614763026296,
      "trend10y_cagr": 73.77430914363686
    },
    {
      "symbol": "TSLA",
      "close": 412.6400146484375,
      "volume": 32641644,
      "turnover_eur": 13469248458.309082,
      "change_pct": 0.48949412895402655,
      "drawdown_pct": -15.767124492630003,
      "trend10y_cagr": 43.53389391269693
    },
    {
      "symbol": "SNDK",
      "close": 603.010009765625,
      "volume": 20013065,
      "turnover_eur": 12068078521.090088,
      "change_pct": 2.102978774681495,
      "drawdown_pct": -13.29959291760171,
      "trend10y_cagr": 32.556638148290574
    },
    {
      "symbol": "MU",
      "close": 421.75909423828125,
      "volume": 24103058,
      "turnover_eur": 10165683910.452759,
      "change_pct": 5.497797670242674,
      "drawdown_pct": -3.6639776157949777,
      "trend10y_cagr": 43.376385203448756
    },
    {
      "symbol": "AMZN",
      "close": 205.42999267578125,
      "volume": 34696811,
      "turnover_eur": 7127765629.602966,
      "change_pct": 2.1277648069427455,
      "drawdown_pct": -19.122050127645174,
      "trend10y_cagr": 22.843859973130943
    },
    {
      "symbol": "META",
      "close": 639.5800170898438,
      "volume": 9888181,
      "turnover_eur": 6324282972.967468,
      "change_pct": 0.0453689362368816,
      "drawdown_pct": -14.912124784649027,
      "trend10y_cagr": 19.97977501209258
    }
  ],
  "most_bought": [
    {
      "symbol": "GPN",
      "close": 80.8949966430664,
      "volume": 5829093,
      "turnover_eur": 471544458.6671219,
      "change_pct": 15.94524944140954,
      "drawdown_pct": -7.717324590949238,
      "trend10y_cagr": 3.381274245107724
    },
    {
      "symbol": "GRMN",
      "close": 237.94000244140625,
      "volume": 1871062,
      "turnover_eur": 445200496.84802246,
      "change_pct": 9.659879770753884,
      "drawdown_pct": -7.235866494578458,
      "trend10y_cagr": 19.292372107527722
    },
    {
      "symbol": "CDNS",
      "close": 309.4200134277344,
      "volume": 2535521,
      "turnover_eur": 784540941.8663025,
      "change_pct": 9.158266688500312,
      "drawdown_pct": -11.946494364799698,
      "trend10y_cagr": 31.005727836150008
    },
    {
      "symbol": "CBRE",
      "close": 152.99000549316406,
      "volume": 2971238,
      "turnover_eur": 454569717.9414978,
      "change_pct": 8.319172715246527,
      "drawdown_pct": -10.85018067185085,
      "trend10y_cagr": 19.740251991564307
    },
    {
      "symbol": "APP",
      "close": 404.989990234375,
      "volume": 3888698,
      "turnover_eur": 1574883765.0444336,
      "change_pct": 7.601356336787959,
      "drawdown_pct": -44.794165251859056,
      "trend10y_cagr": 20.038254431383294
    },
    {
      "symbol": "DASH",
      "close": 173.56500244140625,
      "volume": 5891701,
      "turnover_eur": 1022593098.4490356,
      "change_pct": 6.914504346884525,
      "drawdown_pct": -36.98627617521593,
      "trend10y_cagr": -0.8750448163762914
    }
  ],
  "most_sold": [
    {
      "symbol": "PANW",
      "close": 152.0500030517578,
      "volume": 20369731,
      "turnover_eur": 3097217660.7134857,
      "change_pct": -7.003056237456995,
      "drawdown_pct": -31.31719229464943,
      "trend10y_cagr": 22.18055028303747
    },
    {
      "symbol": "RSG",
      "close": 214.36000061035156,
      "volume": 1670091,
      "turnover_eur": 358000707.77934265,
      "change_pct": -3.087843824615885,
      "drawdown_pct": -5.1378503994484515,
      "trend10y_cagr": 16.73439797041658
    },
    {
      "symbol": "MMM",
      "close": 162.89500427246094,
      "volume": 2558142,
      "turnover_eur": 416708552.01956177,
      "change_pct": -2.8188706493060085,
      "drawdown_pct": -6.709235609037689,
      "trend10y_cagr": 2.196218785805648
    },
    {
      "symbol": "CEG",
      "close": 294.8299865722656,
      "volume": 2173743,
      "turnover_eur": 640884619.5015564,
      "change_pct": -2.699588439235567,
      "drawdown_pct": -27.013249743099344,
      "trend10y_cagr": 21.51565612922257
    },
    {
      "symbol": "T",
      "close": 27.915000915527344,
      "volume": 19592235,
      "turnover_eur": 546917257.9622269,
      "change_pct": -2.667361860210234,
      "drawdown_pct": -3.0729109200613003,
      "trend10y_cagr": -0.008259032813329181
    },
    {
      "symbol": "ETN",
      "close": 381.5899963378906,
      "volume": 1333836,
      "turnover_eur": 508978474.3553467,
      "change_pct": -2.5287987288148805,
      "drawdown_pct": -3.6607841990613066,
      "trend10y_cagr": 21.111690444095778
    }
  ],
  "turnarounds": [
    {
      "symbol": "TTD",
      "close": 25.603500366210938,
      "volume": 10343349,
      "turnover_eur": 264825939.90934753,
      "change_pct": 1.3598580135258653,
      "drawdown_pct": -52.699981782759586,
      "trend10y_cagr": 23.8720385926946
    },
    {
      "symbol": "FISV",
      "close": 63.10499954223633,
      "volume": 5505067,
      "turnover_eur": 347397250.5149803,
      "change_pct": -0.543737141930244,
      "drawdown_pct": -50.130394274011024,
      "trend10y_cagr": 2.739566542026406
    },
    {
      "symbol": "HOOD",
      "close": 76.05999755859375,
      "volume": 17473775,
      "turnover_eur": 1329055283.8394165,
      "change_pct": 0.8218386759319715,
      "drawdown_pct": -50.11150845523633,
      "trend10y_cagr": 8.125230745682966
    },
    {
      "symbol": "ORCL",
      "close": 156.34120178222656,
      "volume": 8962620,
      "turnover_eur": 1401226781.9174194,
      "change_pct": 1.5400406200715162,
      "drawdown_pct": -50.05073425487969,
      "trend10y_cagr": 15.617520522486439
    },
    {
      "symbol": "SMCI",
      "close": 29.829999923706055,
      "volume": 9678109,
      "turnover_eur": 288697990.7316189,
      "change_pct": -0.9299258750238815,
      "drawdown_pct": -48.551224285581476,
      "trend10y_cagr": 24.802582182717714
    },
    {
      "symbol": "PYPL",
      "close": 41.60499954223633,
      "volume": 11884421,
      "turnover_eur": 494451330.2647438,
      "change_pct": 1.9480473957190703,
      "drawdown_pct": -45.07590819506755,
      "trend10y_cagr": 1.3705786625658911
    }
  ]
}