[
  { "symbol": "ADS.DE",  "name": "Adidas" },
  { "symbol": "AIR.DE",  "name": "Airbus" },
  { "symbol": "ALV.DE",  "name": "Allianz" },
  { "symbol": "BAS.DE",  "name": "BASF" },
  { "symbol": "BAYN.DE", "name": "Bayer" },
  { "symbol": "BMW.DE",  "name": "BMW" },
  { "symbol": "CON.DE",  "name": "Continental" },
  { "symbol": "DHER.DE", "name": "Delivery Hero" },
  { "symbol": "DB1.DE",  "name": "Deutsche Boerse" },
  { "symbol": "DBK.DE",  "name": "Deutsche Bank" },
  { "symbol": "DTE.DE",  "name": "Deutsche Telekom" },
  { "symbol": "ENR.DE",  "name": "Siemens Energy" },
  { "symbol": "FRE.DE",  "name": "Fresenius SE" },
  { "symbol": "FME.DE",  "name": "Fresenius Medical Care" },
  { "symbol": "HEI.DE",  "name": "Heidelberg Materials" },
  { "symbol": "HEN3.DE", "name": "Henkel" },
  { "symbol": "HFG.DE",  "name": "HelloFresh" },
  { "symbol": "IFX.DE",  "name": "Infineon" },
  { "symbol": "MRK.DE",  "name": "Merck KGaA" },
  { "symbol": "MBG.DE",  "name": "Mercedes-Benz Group" },
  { "symbol": "MTX.DE",  "name": "MTU Aero Engines" },
  { "symbol": "MUV2.DE", "name": "Munich Re" },
  { "symbol": "PAH3.DE", "name": "Porsche SE" },
  { "symbol": "P911.DE", "name": "Porsche AG" },
  { "symbol": "PUM.DE",  "name": "Puma" },
  { "symbol": "QIA.DE",  "name": "Qiagen" },
  { "symbol": "RHM.DE",  "name": "Rheinmetall" },
  { "symbol": "RWE.DE",  "name": "RWE" },
  { "symbol": "SAP.DE",  "name": "SAP" },
  { "symbol": "SRT3.DE", "name": "Sartorius" },
  { "symbol": "SIE.DE",  "name": "Siemens" },
  { "symbol": "SHL.DE",  "name": "Siemens Healthineers" },
  { "symbol": "SY1.DE",  "name": "Symrise" },
  { "symbol": "TKA.DE",  "name": "ThyssenKrupp" },
  { "symbol": "VNA.DE",  "name": "Vonovia" },
  { "symbol": "VOW3.DE", "name": "Volkswagen Vz" },
  { "symbol": "ZAL.DE",  "name": "Zalando" },
  { "symbol": "LIN.DE",  "name": "Linde plc" },
  { "symbol": "BEI.DE",  "name": "Beiersdorf" },
  { "symbol": "HNR1.DE", "name": "Hannover Rueck" }
]
